<annotations><filename>xshoes_289.JPEG</filename><folder>images</folder><size><width>299</width><height>168</height><depth>3</depth></size><object><name>shoe</name><pose>Unspecified</pose><truncated>0</truncated><difficult>0</difficult><bndbox><xmin>5.00000000007</xmin><ymin>31.0000000001</ymin><xmax>206.0</xmax><ymax>166.0</ymax></bndbox></object><object><name>shoe</name><pose>Unspecified</pose><truncated>0</truncated><difficult>0</difficult><bndbox><xmin>70.0</xmin><ymin>26.0</ymin><xmax>293.0</xmax><ymax>137.0</ymax></bndbox></object><object><name>shoe</name><pose>Unspecified</pose><truncated>0</truncated><difficult>0</difficult><bndbox><xmin>147.0</xmin><ymin>8.00000000008</ymin><xmax>299.0</xmax><ymax>100.0</ymax></bndbox></object></annotations>